pyinsta/__init__.py
pyinsta/connectors.py
pyinsta/functions.py
pyinsta_functions-0.0.1.20.dist-info/METADATA
pyinsta_functions-0.0.1.20.dist-info/WHEEL
pyinsta_functions-0.0.1.20.dist-info/RECORD
