Metadata-Version: 2.1
Name: pyinsta-functions
Version: 0.0.1.20
Requires-Python: >=3.7
Requires-Dist: db-dtypes==1.0.2
Requires-Dist: fastavro==1.5.3
Requires-Dist: gcsfs==2022.5.0
Requires-Dist: google-api-core==2.8.2
Requires-Dist: google-api-python-client==2.54.0
Requires-Dist: google-apitools==0.5.32
Requires-Dist: google-auth-httplib2==0.1.0
Requires-Dist: google-auth-oauthlib==0.5.2
Requires-Dist: google-auth==2.9.1
Requires-Dist: google-cloud-bigquery-storage==2.14.1
Requires-Dist: google-cloud-bigquery==3.2.0
Requires-Dist: google-cloud-core==2.3.2
Requires-Dist: google-cloud-error-reporting==1.6.0
Requires-Dist: google-cloud-pubsub==2.13.4
Requires-Dist: google-cloud-secret-manager==2.12.1
Requires-Dist: google-cloud-storage==2.4.0
Requires-Dist: google-cloud==0.34.0
Requires-Dist: google-crc32c==1.3.0
Requires-Dist: google-resumable-media==2.3.3
Requires-Dist: googleapis-common-protos==1.56.4
Requires-Dist: jsons==1.6.3
Requires-Dist: numpy==1.22.4
Requires-Dist: pandas==1.4.3
Requires-Dist: protobuf==3.20.0
Requires-Dist: pyarrow==8.0.0
Requires-Dist: pytest==7.1.2
Requires-Dist: python-dateutil==2.8.2
Requires-Dist: pytz==2022.1
Requires-Dist: regex==2022.7.25
Requires-Dist: requests
Requires-Dist: requests==2.28.1
